analyzerePythonTools/__init__.py
analyzerePythonTools/combine_elts.py
analyzerePythonTools/visualizations.py
analyzere_extras/__init__.py
analyzere_extras/combine_elts.py
analyzere_extras/visualizations.py
analyzere_tool_extra/__init__.py
analyzere_tool_extra/combine_elts.py
analyzere_tool_extra/visualizations.py
analyzerePythonTools-0.1.5.dist-info/AUTHORS
analyzerePythonTools-0.1.5.dist-info/LICENSE
analyzerePythonTools-0.1.5.dist-info/METADATA
analyzerePythonTools-0.1.5.dist-info/WHEEL
analyzerePythonTools-0.1.5.dist-info/top_level.txt
analyzerePythonTools-0.1.5.dist-info/RECORD
