Metadata-Version: 2.1
Name: analyzerePythonTools
Version: 0.1.5
Summary: Python extras to support the analyzere package
Home-page: https://github.com/analyzere/analyzere-python-extras
Author: Analyze Re
Author-email: support@analyzere.com
License: MIT
Platform: UNKNOWN
Classifier: Development Status :: 3 - Alpha
Classifier: Intended Audience :: Developers
Classifier: License :: OSI Approved :: MIT License
Classifier: Natural Language :: English
Classifier: Programming Language :: Python :: 2
Classifier: Programming Language :: Python :: 2.7
Classifier: Programming Language :: Python :: 3
Classifier: Programming Language :: Python :: 3.4
Classifier: Programming Language :: Python :: 3.8
Classifier: Topic :: Software Development :: Libraries :: Python Modules
Requires-Dist: lazy-object-proxy (<2,>=1.0)
Requires-Dist: requests (<3,>=2.3)
Requires-Dist: six (<2,>=1.9)
Requires-Dist: analyzere (<1,>=0.5.2)
Requires-Dist: graphviz (<1,>=0.5.2)
Requires-Dist: certifi (>=2019.3.9<2020)
Requires-Dist: futures (>=3.3.0<4) ; python_version == "2.7"
